django_admin_bulk_io/__init__.py
django_admin_bulk_io/admin.py
django_admin_bulk_io/apps.py
django_admin_bulk_io/models.py
django_admin_bulk_io/serializer.py
django_admin_bulk_io/views.py
django_admin_bulk_io/migrations/__init__.py
django_admin_bulk_io/static/bulk_io/css/bulkButton.css
django_admin_bulk_io/static/bulk_io/css/bulkToasts.css
django_admin_bulk_io/static/bulk_io/css/modal.css
django_admin_bulk_io/static/bulk_io/js/bootstrap.min.js
django_admin_bulk_io/static/bulk_io/js/bulkAjax.js
django_admin_bulk_io/static/bulk_io/js/bulkToasts.js
django_admin_bulk_io/static/bulk_io/js/bulkUtils.js
django_admin_bulk_io/static/bulk_io/js/jQuery.js
django_admin_bulk_io/templates/admin/change_list.html
django_admin_bulk_io/templates/bulk_io/messages.html
django_admin_bulk_io/templates/bulk_io/modal.html
django_admin_bulk_io/templatetags/__init__.py
django_admin_bulk_io/templatetags/bulk_io_urls_list.py
django_admin_bulk_io/templatetags/render_model_fields.py
django_admin_bulk_io/utils/__init__.py
django_admin_bulk_io/utils/bulkio_threading.py
django_admin_bulk_io/utils/constants.py
django_admin_bulk_io/utils/exceptions.py
django_admin_bulk_io/utils/response.py
django_admin_bulk_io/utils/utils.py
django_admin_bulk_io-1.3.dist-info/LICENSE
django_admin_bulk_io-1.3.dist-info/METADATA
django_admin_bulk_io-1.3.dist-info/WHEEL
django_admin_bulk_io-1.3.dist-info/top_level.txt
django_admin_bulk_io-1.3.dist-info/RECORD
