Metadata-Version: 2.1
Name: django-admin-bulk-io
Version: 1.3
Summary: This package allows you to import and export data in your Django admin.
Home-page: https://github.com/mohitprajapat2001/django-admin-bulk-io
Author: Mohit Prajapat
Author-email: mohitdevelopment2001@gmail.com
Classifier: Framework :: Django
Classifier: Intended Audience :: Developers
Classifier: License :: OSI Approved :: MIT License
Classifier: Operating System :: OS Independent
Classifier: Programming Language :: Python :: 3
Classifier: Programming Language :: Python :: 3.8
Classifier: Programming Language :: Python :: 3.9
Classifier: Programming Language :: Python :: 3.10
Classifier: Programming Language :: Python :: 3.11
License-File: LICENSE
Requires-Dist: django>=5.1
Requires-Dist: djangorestframework>=3.15.2
Requires-Dist: pandas>=2.2.3
